{
  "ejercicio_id": "m09",
  "secuencia": [
    {
      "frame_index": 0,
      "puntos_clave": {
        "nariz": {
          "x": 0.49157488346099854,
          "y": 0.7471738457679749,
          "z": -0.7902351
        },
        "hombro_d": {
          "x": 0.35426804423332214,
          "y": 0.5608577728271484,
          "z": -0.20926517
        },
        "codo_d": {
          "x": 0.20367106795310974,
          "y": 0.37754619121551514,
          "z": -0.51952326
        },
        "muneca_d": {
          "x": 0.18224556744098663,
          "y": 0.1709461510181427,
          "z": -1.1888871
        },
        "hombro_i": {
          "x": 0.63791823387146,
          "y": 0.5683993101119995,
          "z": -0.20926517
        },
        "codo_i": {
          "x": 0.7997055053710938,
          "y": 0.3630713224411011,
          "z": -0.51952326
        },
        "muneca_i": {
          "x": 0.8193553686141968,
          "y": 0.19217224419116974,
          "z": -1.1888871
        }
      }
    },
    {
      "frame_index": 1,
      "puntos_clave": {
        "nariz": {
          "x": 0.49463847279548645,
          "y": 0.7321288585662842,
          "z": -0.7902351
        },
        "hombro_d": {
          "x": 0.3441947102546692,
          "y": 0.5443394184112549,
          "z": -0.20926517
        },
        "codo_d": {
          "x": 0.20302565395832062,
          "y": 0.3585406243801117,
          "z": -0.51952326
        },
        "muneca_d": {
          "x": 0.18691477179527283,
          "y": 0.17201325297355652,
          "z": -1.1888871
        },
        "hombro_i": {
          "x": 0.6493455767631531,
          "y": 0.5652682781219482,
          "z": -0.20926517
        },
        "codo_i": {
          "x": 0.8094116449356079,
          "y": 0.36051487922668457,
          "z": -0.51952326
        },
        "muneca_i": {
          "x": 0.8229393362998962,
          "y": 0.1879758983850479,
          "z": -1.1888871
        }
      }
    },
    {
      "frame_index": 2,
      "puntos_clave": {
        "nariz": {
          "x": 0.511682391166687,
          "y": 0.753930926322937,
          "z": -0.7902351
        },
        "hombro_d": {
          "x": 0.3507843315601349,
          "y": 0.5589026212692261,
          "z": -0.20926517
        },
        "codo_d": {
          "x": 0.1965796798467636,
          "y": 0.34304922819137573,
          "z": -0.51952326
        },
        "muneca_d": {
          "x": 0.1660645306110382,
          "y": 0.18674834072589874,
          "z": -1.1888871
        },
        "hombro_i": {
          "x": 0.6254581809043884,
          "y": 0.5737412571907043,
          "z": -0.20926517
        },
        "codo_i": {
          "x": 0.800475537776947,
          "y": 0.3544413149356842,
          "z": -0.51952326
        },
        "muneca_i": {
          "x": 0.8197093605995178,
          "y": 0.16852670907974243,
          "z": -1.1888871
        }
      }
    },
    {
      "frame_index": 3,
      "puntos_clave": {
        "nariz": {
          "x": 0.4960606098175049,
          "y": 0.7298876047134399,
          "z": -0.7902351
        },
        "hombro_d": {
          "x": 0.3754827380180359,
          "y": 0.5556463599205017,
          "z": -0.20926517
        },
        "codo_d": {
          "x": 0.20326127111911774,
          "y": 0.363476425409317,
          "z": -0.51952326
        },
        "muneca_d": {
          "x": 0.1692943572998047,
          "y": 0.1659141480922699,
          "z": -1.1888871
        },
        "hombro_i": {
          "x": 0.6328766942024231,
          "y": 0.5564267635345459,
          "z": -0.20926517
        },
        "codo_i": {
          "x": 0.7911649346351624,
          "y": 0.34173017740249634,
          "z": -0.51952326
        },
        "muneca_i": {
          "x": 0.8384697437286377,
          "y": 0.1632191389799118,
          "z": -1.1888871
        }
      }
    },
    {
      "frame_index": 4,
      "puntos_clave": {
        "nariz": {
          "x": 0.4777727723121643,
          "y": 0.7289824485778809,
          "z": -0.7902351
        },
        "hombro_d": {
          "x": 0.3528841435909271,
          "y": 0.5393479466438293,
          "z": -0.20926517
        },
        "codo_d": {
          "x": 0.21110579371452332,
          "y": 0.34981808066368103,
          "z": -0.51952326
        },
        "muneca_d": {
          "x": 0.14667432010173798,
          "y": 0.17978279292583466,
          "z": -1.1888871
        },
        "hombro_i": {
          "x": 0.6303033828735352,
          "y": 0.5578043460845947,
          "z": -0.20926517
        },
        "codo_i": {
          "x": 0.8092910051345825,
          "y": 0.34247687458992004,
          "z": -0.51952326
        },
        "muneca_i": {
          "x": 0.8516126871109009,
          "y": 0.1874198317527771,
          "z": -1.1888871
        }
      }
    },
    {
      "frame_index": 5,
      "puntos_clave": {
        "nariz": {
          "x": 0.5117152333259583,
          "y": 0.7338859438896179,
          "z": -0.7902351
        },
        "hombro_d": {
          "x": 0.35791414976119995,
          "y": 0.5509365200996399,
          "z": -0.20926517
        },
        "codo_d": {
          "x": 0.18704849481582642,
          "y": 0.35511118173599243,
          "z": -0.51952326
        },
        "muneca_d": {
          "x": 0.14874811470508575,
          "y": 0.16498281061649323,
          "z": -1.1888871
        },
        "hombro_i": {
          "x": 0.6314184665679932,
          "y": 0.5618537664413452,
          "z": -0.20926517
        },
        "codo_i": {
          "x": 0.8033236265182495,
          "y": 0.3748199939727783,
          "z": -0.51952326
        },
        "muneca_i": {
          "x": 0.8486392498016357,
          "y": 0.19084008038043976,
          "z": -1.1888871
        }
      }
    },
    {
      "frame_index": 6,
      "puntos_clave": {
        "nariz": {
          "x": 0.48414963483810425,
          "y": 0.7458748817443848,
          "z": -0.7902351
        },
        "hombro_d": {
          "x": 0.374067097902298,
          "y": 0.5642862915992737,
          "z": -0.20926517
        },
        "codo_d": {
          "x": 0.18508200347423553,
          "y": 0.3568238914012909,
          "z": -0.51952326
        },
        "muneca_d": {
          "x": 0.15579666197299957,
          "y": 0.1795799285173416,
          "z": -1.1888871
        },
        "hombro_i": {
          "x": 0.6247537136077881,
          "y": 0.5797114372253418,
          "z": -0.20926517
        },
        "codo_i": {
          "x": 0.7982503175735474,
          "y": 0.35431230068206787,
          "z": -0.51952326
        },
        "muneca_i": {
          "x": 0.8385526537895203,
          "y": 0.16758830845355988,
          "z": -1.1888871
        }
      }
    },
    {
      "frame_index": 7,
      "puntos_clave": {
        "nariz": {
          "x": 0.49923527240753174,
          "y": 0.7170068621635437,
          "z": -0.7902351
        },
        "hombro_d": {
          "x": 0.36805403232574463,
          "y": 0.5470299124717712,
          "z": -0.20926517
        },
        "codo_d": {
          "x": 0.19962751865386963,
          "y": 0.36457327008247375,
          "z": -0.51952326
        },
        "muneca_d": {
          "x": 0.15643033385276794,
          "y": 0.177987203001976,
          "z": -1.1888871
        },
        "hombro_i": {
          "x": 0.6316137909889221,
          "y": 0.5437784790992737,
          "z": -0.20926517
        },
        "codo_i": {
          "x": 0.8133866786956787,
          "y": 0.3860972821712494,
          "z": -0.51952326
        },
        "muneca_i": {
          "x": 0.866787314414978,
          "y": 0.19233690202236176,
          "z": -1.1888871
        }
      }
    },
    {
      "frame_index": 8,
      "puntos_clave": {
        "nariz": {
          "x": 0.49583330750465393,
          "y": 0.7440791726112366,
          "z": -0.7902351
        },
        "hombro_d": {
          "x": 0.36012011766433716,
          "y": 0.5621175765991211,
          "z": -0.20926517
        },
        "codo_d": {
          "x": 0.19152557849884033,
          "y": 0.3738902807235718,
          "z": -0.51952326
        },
        "muneca_d": {
          "x": 0.14650698006153107,
          "y": 0.1814945638179779,
          "z": -1.1888871
        },
        "hombro_i": {
          "x": 0.6509423851966858,
          "y": 0.5633656978607178,
          "z": -0.20926517
        },
        "codo_i": {
          "x": 0.8117502927780151,
          "y": 0.3786357045173645,
          "z": -0.51952326
        },
        "muneca_i": {
          "x": 0.8479883074760437,
          "y": 0.18183033168315887,
          "z": -1.1888871
        }
      }
    },
    {
      "frame_index": 9,
      "puntos_clave": {
        "nariz": {
          "x": 0.4996665120124817,
          "y": 0.7256446480751038,
          "z": -0.7902351
        },
        "hombro_d": {
          "x": 0.36344394087791443,
          "y": 0.5665269494056702,
          "z": -0.20926517
        },
        "codo_d": {
          "x": 0.16054357588291168,
          "y": 0.3780631721019745,
          "z": -0.51952326
        },
        "muneca_d": {
          "x": 0.14640063047409058,
          "y": 0.2063767910003662,
          "z": -1.1888871
        },
        "hombro_i": {
          "x": 0.6503450870513916,
          "y": 0.5559330582618713,
          "z": -0.20926517
        },
        "codo_i": {
          "x": 0.8084706664085388,
          "y": 0.39526087045669556,
          "z": -0.51952326
        },
        "muneca_i": {
          "x": 0.8738142251968384,
          "y": 0.20270612835884094,
          "z": -1.1888871
        }
      }
    },
    {
      "frame_index": 10,
      "puntos_clave": {
        "nariz": {
          "x": 0.485851526260376,
          "y": 0.7376722097396851,
          "z": -0.7902351
        },
        "hombro_d": {
          "x": 0.3660601079463959,
          "y": 0.54863041639328,
          "z": -0.20926517
        },
        "codo_d": {
          "x": 0.17802688479423523,
          "y": 0.36893120408058167,
          "z": -0.51952326
        },
        "muneca_d": {
          "x": 0.11336133629083633,
          "y": 0.1988212764263153,
          "z": -1.1888871
        },
        "hombro_i": {
          "x": 0.6345813870429993,
          "y": 0.5573751330375671,
          "z": -0.20926517
        },
        "codo_i": {
          "x": 0.8378067016601562,
          "y": 0.3590776324272156,
          "z": -0.51952326
        },
        "muneca_i": {
          "x": 0.8730449080467224,
          "y": 0.19993308186531067,
          "z": -1.1888871
        }
      }
    },
    {
      "frame_index": 11,
      "puntos_clave": {
        "nariz": {
          "x": 0.4965309202671051,
          "y": 0.7308282256126404,
          "z": -0.7902351
        },
        "hombro_d": {
          "x": 0.3537960946559906,
          "y": 0.5512391328811646,
          "z": -0.20926517
        },
        "codo_d": {
          "x": 0.1935153603553772,
          "y": 0.36949217319488525,
          "z": -0.51952326
        },
        "muneca_d": {
          "x": 0.08643127232789993,
          "y": 0.2261802852153778,
          "z": -1.1888871
        },
        "hombro_i": {
          "x": 0.6485321521759033,
          "y": 0.5492966771125793,
          "z": -0.20926517
        },
        "codo_i": {
          "x": 0.8203091621398926,
          "y": 0.38743332028388977,
          "z": -0.51952326
        },
        "muneca_i": {
          "x": 0.8866764307022095,
          "y": 0.21041369438171387,
          "z": -1.1888871
        }
      }
    },
    {
      "frame_index": 12,
      "puntos_clave": {
        "nariz": {
          "x": 0.5215407609939575,
          "y": 0.7467440962791443,
          "z": -0.7902351
        },
        "hombro_d": {
          "x": 0.36254796385765076,
          "y": 0.5319973230361938,
          "z": -0.20926517
        },
        "codo_d": {
          "x": 0.14657223224639893,
          "y": 0.3897307813167572,
          "z": -0.51952326
        },
        "muneca_d": {
          "x": 0.11314705014228821,
          "y": 0.2080284208059311,
          "z": -1.1888871
        },
        "hombro_i": {
          "x": 0.6342137455940247,
          "y": 0.5502130389213562,
          "z": -0.20926517
        },
        "codo_i": {
          "x": 0.8224316239356995,
          "y": 0.4288046658039093,
          "z": -0.51952326
        },
        "muneca_i": {
          "x": 0.879058837890625,
          "y": 0.22092288732528687,
          "z": -1.1888871
        }
      }
    },
    {
      "frame_index": 13,
      "puntos_clave": {
        "nariz": {
          "x": 0.509721040725708,
          "y": 0.725737452507019,
          "z": -0.7902351
        },
        "hombro_d": {
          "x": 0.35377147793769836,
          "y": 0.5469380021095276,
          "z": -0.20926517
        },
        "codo_d": {
          "x": 0.16429591178894043,
          "y": 0.40670955181121826,
          "z": -0.51952326
        },
        "muneca_d": {
          "x": 0.08871803432703018,
          "y": 0.22127604484558105,
          "z": -1.1888871
        },
        "hombro_i": {
          "x": 0.6355307102203369,
          "y": 0.5529702305793762,
          "z": -0.20926517
        },
        "codo_i": {
          "x": 0.8390855193138123,
          "y": 0.4022403359413147,
          "z": -0.51952326
        },
        "muneca_i": {
          "x": 0.9212262630462646,
          "y": 0.23237399756908417,
          "z": -1.1888871
        }
      }
    },
    {
      "frame_index": 14,
      "puntos_clave": {
        "nariz": {
          "x": 0.4869946241378784,
          "y": 0.7270247936248779,
          "z": -0.7902351
        },
        "hombro_d": {
          "x": 0.3684260845184326,
          "y": 0.5479445457458496,
          "z": -0.20926517
        },
        "codo_d": {
          "x": 0.1690576672554016,
          "y": 0.3846903443336487,
          "z": -0.51952326
        },
        "muneca_d": {
          "x": 0.07742758095264435,
          "y": 0.23156793415546417,
          "z": -1.1888871
        },
        "hombro_i": {
          "x": 0.6398584246635437,
          "y": 0.5639010667800903,
          "z": -0.20926517
        },
        "codo_i": {
          "x": 0.8467090725898743,
          "y": 0.3873445391654968,
          "z": -0.51952326
        },
        "muneca_i": {
          "x": 0.9264554977416992,
          "y": 0.23286277055740356,
          "z": -1.1888871
        }
      }
    },
    {
      "frame_index": 15,
      "puntos_clave": {
        "nariz": {
          "x": 0.5138782262802124,
          "y": 0.7552133202552795,
          "z": -0.7902351
        },
        "hombro_d": {
          "x": 0.36439430713653564,
          "y": 0.5668991208076477,
          "z": -0.20926517
        },
        "codo_d": {
          "x": 0.12876036763191223,
          "y": 0.3943729102611542,
          "z": -0.51952326
        },
        "muneca_d": {
          "x": 0.06787397712469101,
          "y": 0.21746297180652618,
          "z": -1.1888871
        },
        "hombro_i": {
          "x": 0.6253328323364258,
          "y": 0.5805668234825134,
          "z": -0.20926517
        },
        "codo_i": {
          "x": 0.8583475351333618,
          "y": 0.40561816096305847,
          "z": -0.51952326
        },
        "muneca_i": {
          "x": 0.9222432971000671,
          "y": 0.24302248656749725,
          "z": -1.1888871
        }
      }
    },
    {
      "frame_index": 16,
      "puntos_clave": {
        "nariz": {
          "x": 0.5009188055992126,
          "y": 0.744884192943573,
          "z": -0.7902351
        },
        "hombro_d": {
          "x": 0.35178086161613464,
          "y": 0.5726817846298218,
          "z": -0.20926517
        },
        "codo_d": {
          "x": 0.13469448685646057,
          "y": 0.3971504271030426,
          "z": -0.51952326
        },
        "muneca_d": {
          "x": 0.05462062731385231,
          "y": 0.2524735927581787,
          "z": -1.1888871
        },
        "hombro_i": {
          "x": 0.6574674844741821,
          "y": 0.5436117649078369,
          "z": -0.20926517
        },
        "codo_i": {
          "x": 0.8391200304031372,
          "y": 0.42597368359565735,
          "z": -0.51952326
        },
        "muneca_i": {
          "x": 0.9397105574607849,
          "y": 0.23668426275253296,
          "z": -1.1888871
        }
      }
    },
    {
      "frame_index": 17,
      "puntos_clave": {
        "nariz": {
          "x": 0.5031346678733826,
          "y": 0.7525126338005066,
          "z": -0.7902351
        },
        "hombro_d": {
          "x": 0.36284518241882324,
          "y": 0.5467205047607422,
          "z": -0.20926517
        },
        "codo_d": {
          "x": 0.13116416335105896,
          "y": 0.4091219902038574,
          "z": -0.51952326
        },
        "muneca_d": {
          "x": 0.062363579869270325,
          "y": 0.25221624970436096,
          "z": -1.1888871
        },
        "hombro_i": {
          "x": 0.6303461790084839,
          "y": 0.5680820941925049,
          "z": -0.20926517
        },
        "codo_i": {
          "x": 0.8619306683540344,
          "y": 0.41655153036117554,
          "z": -0.51952326
        },
        "muneca_i": {
          "x": 0.9645950794219971,
          "y": 0.26339587569236755,
          "z": -1.1888871
        }
      }
    },
    {
      "frame_index": 18,
      "puntos_clave": {
        "nariz": {
          "x": 0.48655638098716736,
          "y": 0.7193102836608887,
          "z": -0.7902351
        },
        "hombro_d": {
          "x": 0.3688265383243561,
          "y": 0.5455831289291382,
          "z": -0.20926517
        },
        "codo_d": {
          "x": 0.14543795585632324,
          "y": 0.4107058644294739,
          "z": -0.51952326
        },
        "muneca_d": {
          "x": 0.04228176176548004,
          "y": 0.2645014524459839,
          "z": -1.1888871
        },
        "hombro_i": {
          "x": 0.6411629319190979,
          "y": 0.5447492003440857,
          "z": -0.20926517
        },
        "codo_i": {
          "x": 0.8664214611053467,
          "y": 0.4398074150085449,
          "z": -0.51952326
        },
        "muneca_i": {
          "x": 0.9781924486160278,
          "y": 0.2690892219543457,
          "z": -1.1888871
        }
      }
    },
    {
      "frame_index": 19,
      "puntos_clave": {
        "nariz": {
          "x": 0.4754795432090759,
          "y": 0.7368061542510986,
          "z": -0.7902351
        },
        "hombro_d": {
          "x": 0.35766083002090454,
          "y": 0.5556203722953796,
          "z": -0.20926517
        },
        "codo_d": {
          "x": 0.12997104227542877,
          "y": 0.4251546561717987,
          "z": -0.51952326
        },
        "muneca_d": {
          "x": 0.009005438536405563,
          "y": 0.28548428416252136,
          "z": -1.1888871
        },
        "hombro_i": {
          "x": 0.6206491589546204,
          "y": 0.5400784015655518,
          "z": -0.20926517
        },
        "codo_i": {
          "x": 0.8610863089561462,
          "y": 0.4519155025482178,
          "z": -0.51952326
        },
        "muneca_i": {
          "x": 0.9623913764953613,
          "y": 0.28424423933029175,
          "z": -1.1888871
        }
      }
    },
    {
      "frame_index": 20,
      "puntos_clave": {
        "nariz": {
          "x": 0.49730849266052246,
          "y": 0.7585896849632263,
          "z": -0.7902351
        },
        "hombro_d": {
          "x": 0.35673394799232483,
          "y": 0.5227760672569275,
          "z": -0.20926517
        },
        "codo_d": {
          "x": 0.110977903008461,
          "y": 0.42422589659690857,
          "z": -0.51952326
        },
        "muneca_d": {
          "x": 0.0034089554101228714,
          "y": 0.303972989320755,
          "z": -1.1888871
        },
        "hombro_i": {
          "x": 0.6467790603637695,
          "y": 0.5674071311950684,
          "z": -0.20926517
        },
        "codo_i": {
          "x": 0.8664344549179077,
          "y": 0.443260133266449,
          "z": -0.51952326
        },
        "muneca_i": {
          "x": 0.9863166809082031,
          "y": 0.31545886397361755,
          "z": -1.1888871
        }
      }
    },
    {
      "frame_index": 21,
      "puntos_clave": {
        "nariz": {
          "x": 0.5010740160942078,
          "y": 0.7490746974945068,
          "z": -0.7902351
        },
        "hombro_d": {
          "x": 0.3544369637966156,
          "y": 0.5335158705711365,
          "z": -0.20926517
        },
        "codo_d": {
          "x": 0.14296725392341614,
          "y": 0.4205765724182129,
          "z": -0.51952326
        },
        "muneca_d": {
          "x": -0.004932862240821123,
          "y": 0.32008659839630127,
          "z": -1.1888871
        },
        "hombro_i": {
          "x": 0.6509770154953003,
          "y": 0.5682713389396667,
          "z": -0.20926517
        },
        "codo_i": {
          "x": 0.8929524421691895,
          "y": 0.4786866307258606,
          "z": -0.51952326
        },
        "muneca_i": {
          "x": 1.00833261013031,
          "y": 0.3286629915237427,
          "z": -1.1888871
        }
      }
    },
    {
      "frame_index": 22,
      "puntos_clave": {
        "nariz": {
          "x": 0.5155820846557617,
          "y": 0.7758833169937134,
          "z": -0.7902351
        },
        "hombro_d": {
          "x": 0.3624730110168457,
          "y": 0.5353488922119141,
          "z": -0.20926517
        },
        "codo_d": {
          "x": 0.1258455216884613,
          "y": 0.47125083208084106,
          "z": -0.51952326
        },
        "muneca_d": {
          "x": 1.0627321898937225e-05,
          "y": 0.30727559328079224,
          "z": -1.1888871
        },
        "hombro_i": {
          "x": 0.6199461221694946,
          "y": 0.5554154515266418,
          "z": -0.20926517
        },
        "codo_i": {
          "x": 0.8835473656654358,
          "y": 0.4826680123806,
          "z": -0.51952326
        },
        "muneca_i": {
          "x": 1.0045846700668335,
          "y": 0.35343822836875916,
          "z": -1.1888871
        }
      }
    },
    {
      "frame_index": 23,
      "puntos_clave": {
        "nariz": {
          "x": 0.45903536677360535,
          "y": 0.7326708436012268,
          "z": -0.7902351
        },
        "hombro_d": {
          "x": 0.35957109928131104,
          "y": 0.5386983752250671,
          "z": -0.20926517
        },
        "codo_d": {
          "x": 0.11384087055921555,
          "y": 0.460910826921463,
          "z": -0.51952326
        },
        "muneca_d": {
          "x": -0.011492747813463211,
          "y": 0.35061222314834595,
          "z": -1.1888871
        },
        "hombro_i": {
          "x": 0.6342686414718628,
          "y": 0.5381169319152832,
          "z": -0.20926517
        },
        "codo_i": {
          "x": 0.8637630343437195,
          "y": 0.4744804799556732,
          "z": -0.51952326
        },
        "muneca_i": {
          "x": 1.0264118909835815,
          "y": 0.35266363620758057,
          "z": -1.1888871
        }
      }
    },
    {
      "frame_index": 24,
      "puntos_clave": {
        "nariz": {
          "x": 0.5003035664558411,
          "y": 0.7314675450325012,
          "z": -0.7902351
        },
        "hombro_d": {
          "x": 0.3595103919506073,
          "y": 0.5386012196540833,
          "z": -0.20926517
        },
        "codo_d": {
          "x": 0.10465741902589798,
          "y": 0.5028188824653625,
          "z": -0.51952326
        },
        "muneca_d": {
          "x": -0.02455959841609001,
          "y": 0.35936659574508667,
          "z": -1.1888871
        },
        "hombro_i": {
          "x": 0.6402891874313354,
          "y": 0.5498687624931335,
          "z": -0.20926517
        },
        "codo_i": {
          "x": 0.8847132921218872,
          "y": 0.5049118995666504,
          "z": -0.51952326
        },
        "muneca_i": {
          "x": 1.0422110557556152,
          "y": 0.383094847202301,
          "z": -1.1888871
        }
      }
    },
    {
      "frame_index": 25,
      "puntos_clave": {
        "nariz": {
          "x": 0.48650410771369934,
          "y": 0.7309135794639587,
          "z": -0.7902351
        },
        "hombro_d": {
          "x": 0.3579695522785187,
          "y": 0.5373966097831726,
          "z": -0.20926517
        },
        "codo_d": {
          "x": 0.12095144391059875,
          "y": 0.512901782989502,
          "z": -0.51952326
        },
        "muneca_d": {
          "x": -0.03702985495328903,
          "y": 0.3792838156223297,
          "z": -1.1888871
        },
        "hombro_i": {
          "x": 0.6372385621070862,
          "y": 0.5586737990379333,
          "z": -0.20926517
        },
        "codo_i": {
          "x": 0.8948057889938354,
          "y": 0.4903496205806732,
          "z": -0.51952326
        },
        "muneca_i": {
          "x": 1.031719446182251,
          "y": 0.40932169556617737,
          "z": -1.1888871
        }
      }
    },
    {
      "frame_index": 26,
      "puntos_clave": {
        "nariz": {
          "x": 0.4649365246295929,
          "y": 0.7409634590148926,
          "z": -0.7902351
        },
        "hombro_d": {
          "x": 0.3725573718547821,
          "y": 0.5534607768058777,
          "z": -0.20926517
        },
        "codo_d": {
          "x": 0.10243813693523407,
          "y": 0.5146436095237732,
          "z": -0.51952326
        },
        "muneca_d": {
          "x": -0.04946067929267883,
          "y": 0.37959587574005127,
          "z": -1.1888871
        },
        "hombro_i": {
          "x": 0.6302929520606995,
          "y": 0.5681235194206238,
          "z": -0.20926517
        },
        "codo_i": {
          "x": 0.9028864502906799,
          "y": 0.5241488814353943,
          "z": -0.51952326
        },
        "muneca_i": {
          "x": 1.0399070978164673,
          "y": 0.4176553189754486,
          "z": -1.1888871
        }
      }
    },
    {
      "frame_index": 27,
      "puntos_clave": {
        "nariz": {
          "x": 0.5023249387741089,
          "y": 0.7382296323776245,
          "z": -0.7902351
        },
        "hombro_d": {
          "x": 0.3542387783527374,
          "y": 0.5420995950698853,
          "z": -0.20926517
        },
        "codo_d": {
          "x": 0.11812327802181244,
          "y": 0.5316368937492371,
          "z": -0.51952326
        },
        "muneca_d": {
          "x": -0.057865142822265625,
          "y": 0.41915440559387207,
          "z": -1.1888871
        },
        "hombro_i": {
          "x": 0.6317618489265442,
          "y": 0.5662552118301392,
          "z": -0.20926517
        },
        "codo_i": {
          "x": 0.9102755188941956,
          "y": 0.5284817814826965,
          "z": -0.51952326
        },
        "muneca_i": {
          "x": 1.0640510320663452,
          "y": 0.4350268244743347,
          "z": -1.1888871
        }
      }
    },
    {
      "frame_index": 28,
      "puntos_clave": {
        "nariz": {
          "x": 0.5010825991630554,
          "y": 0.7274777889251709,
          "z": -0.7902351
        },
        "hombro_d": {
          "x": 0.3671475052833557,
          "y": 0.5481300950050354,
          "z": -0.20926517
        },
        "codo_d": {
          "x": 0.11471346020698547,
          "y": 0.5303090214729309,
          "z": -0.51952326
        },
        "muneca_d": {
          "x": -0.04202673211693764,
          "y": 0.44893136620521545,
          "z": -1.1888871
        },
        "hombro_i": {
          "x": 0.6395549178123474,
          "y": 0.5602096319198608,
          "z": -0.20926517
        },
        "codo_i": {
          "x": 0.9188175201416016,
          "y": 0.5449545979499817,
          "z": -0.51952326
        },
        "muneca_i": {
          "x": 1.0527520179748535,
          "y": 0.45126304030418396,
          "z": -1.1888871
        }
      }
    },
    {
      "frame_index": 29,
      "puntos_clave": {
        "nariz": {
          "x": 0.5001564025878906,
          "y": 0.7344911694526672,
          "z": -0.7902351
        },
        "hombro_d": {
          "x": 0.38066262006759644,
          "y": 0.5318514108657837,
          "z": -0.20926517
        },
        "codo_d": {
          "x": 0.07880973815917969,
          "y": 0.5461862683296204,
          "z": -0.51952326
        },
        "muneca_d": {
          "x": -0.06084960699081421,
          "y": 0.44364866614341736,
          "z": -1.1888871
        },
        "hombro_i": {
          "x": 0.6414468884468079,
          "y": 0.5530444979667664,
          "z": -0.20926517
        },
        "codo_i": {
          "x": 0.8814511299133301,
          "y": 0.5570730566978455,
          "z": -0.51952326
        },
        "muneca_i": {
          "x": 1.059030532836914,
          "y": 0.4515535235404968,
          "z": -1.1888871
        }
      }
    },
    {
      "frame_index": 30,
      "puntos_clave": {
        "nariz": {
          "x": 0.5005409717559814,
          "y": 0.738490879535675,
          "z": -0.7902351
        },
        "hombro_d": {
          "x": 0.3867989778518677,
          "y": 0.5183637738227844,
          "z": -0.20926517
        },
        "codo_d": {
          "x": 0.10528244078159332,
          "y": 0.5771604180335999,
          "z": -0.51952326
        },
        "muneca_d": {
          "x": -0.07667282223701477,
          "y": 0.48861026763916016,
          "z": -1.1888871
        },
        "hombro_i": {
          "x": 0.6490610241889954,
          "y": 0.5575883984565735,
          "z": -0.20926517
        },
        "codo_i": {
          "x": 0.8861956596374512,
          "y": 0.5593788623809814,
          "z": -0.51952326
        },
        "muneca_i": {
          "x": 1.0623259544372559,
          "y": 0.4976349472999573,
          "z": -1.1888871
        }
      }
    },
    {
      "frame_index": 31,
      "puntos_clave": {
        "nariz": {
          "x": 0.5008498430252075,
          "y": 0.7253206968307495,
          "z": -0.7902351
        },
        "hombro_d": {
          "x": 0.36924511194229126,
          "y": 0.5199486613273621,
          "z": -0.20926517
        },
        "codo_d": {
          "x": 0.12167353928089142,
          "y": 0.5815852284431458,
          "z": -0.51952326
        },
        "muneca_d": {
          "x": -0.08340244740247726,
          "y": 0.4948827028274536,
          "z": -1.1888871
        },
        "hombro_i": {
          "x": 0.6278358101844788,
          "y": 0.5498316287994385,
          "z": -0.20926517
        },
        "codo_i": {
          "x": 0.9045602679252625,
          "y": 0.5936257839202881,
          "z": -0.51952326
        },
        "muneca_i": {
          "x": 1.0589481592178345,
          "y": 0.5066244006156921,
          "z": -1.1888871
        }
      }
    },
    {
      "frame_index": 32,
      "puntos_clave": {
        "nariz": {
          "x": 0.4903559684753418,
          "y": 0.7480090856552124,
          "z": -0.7902351
        },
        "hombro_d": {
          "x": 0.356788694858551,
          "y": 0.5283868312835693,
          "z": -0.20926517
        },
        "codo_d": {
          "x": 0.0690029188990593,
          "y": 0.5972830057144165,
          "z": -0.51952326
        },
        "muneca_d": {
          "x": -0.059706758707761765,
          "y": 0.5235213041305542,
          "z": -1.1888871
        },
        "hombro_i": {
          "x": 0.6127637624740601,
          "y": 0.5561366677284241,
          "z": -0.20926517
        },
        "codo_i": {
          "x": 0.8751984238624573,
          "y": 0.5692311525344849,
          "z": -0.51952326
        },
        "muneca_i": {
          "x": 1.0630171298980713,
          "y": 0.5477281808853149,
          "z": -1.1888871
        }
      }
    },
    {
      "frame_index": 33,
      "puntos_clave": {
        "nariz": {
          "x": 0.5271966457366943,
          "y": 0.7355574369430542,
          "z": -0.7902351
        },
        "hombro_d": {
          "x": 0.3567520081996918,
          "y": 0.5231703519821167,
          "z": -0.20926517
        },
        "codo_d": {
          "x": 0.1010737344622612,
          "y": 0.60612952709198,
          "z": -0.51952326
        },
        "muneca_d": {
          "x": -0.06699278205633163,
          "y": 0.5469111204147339,
          "z": -1.1888871
        },
        "hombro_i": {
          "x": 0.6141999363899231,
          "y": 0.5486339330673218,
          "z": -0.20926517
        },
        "codo_i": {
          "x": 0.9097609519958496,
          "y": 0.6279118061065674,
          "z": -0.51952326
        },
        "muneca_i": {
          "x": 1.0697425603866577,
          "y": 0.5467748045921326,
          "z": -1.1888871
        }
      }
    },
    {
      "frame_index": 34,
      "puntos_clave": {
        "nariz": {
          "x": 0.5209528207778931,
          "y": 0.7323529720306396,
          "z": -0.7902351
        },
        "hombro_d": {
          "x": 0.3521876633167267,
          "y": 0.5262425541877747,
          "z": -0.20926517
        },
        "codo_d": {
          "x": 0.08791346848011017,
          "y": 0.5856713056564331,
          "z": -0.51952326
        },
        "muneca_d": {
          "x": -0.07822734117507935,
          "y": 0.545393705368042,
          "z": -1.1888871
        },
        "hombro_i": {
          "x": 0.6271908283233643,
          "y": 0.5524642467498779,
          "z": -0.20926517
        },
        "codo_i": {
          "x": 0.8828760981559753,
          "y": 0.6088770031929016,
          "z": -0.51952326
        },
        "muneca_i": {
          "x": 1.0371700525283813,
          "y": 0.5529782772064209,
          "z": -1.1888871
        }
      }
    },
    {
      "frame_index": 35,
      "puntos_clave": {
        "nariz": {
          "x": 0.519655168056488,
          "y": 0.7452763915061951,
          "z": -0.7902351
        },
        "hombro_d": {
          "x": 0.3600738048553467,
          "y": 0.5130125880241394,
          "z": -0.20926517
        },
        "codo_d": {
          "x": 0.1212395578622818,
          "y": 0.6171953082084656,
          "z": -0.51952326
        },
        "muneca_d": {
          "x": -0.06653347611427307,
          "y": 0.5643532872200012,
          "z": -1.1888871
        },
        "hombro_i": {
          "x": 0.6298889517784119,
          "y": 0.5730804800987244,
          "z": -0.20926517
        },
        "codo_i": {
          "x": 0.9000482559204102,
          "y": 0.6248547434806824,
          "z": -0.51952326
        },
        "muneca_i": {
          "x": 1.0607538223266602,
          "y": 0.5844881534576416,
          "z": -1.1888871
        }
      }
    },
    {
      "frame_index": 36,
      "puntos_clave": {
        "nariz": {
          "x": 0.5070478320121765,
          "y": 0.7334057092666626,
          "z": -0.7902351
        },
        "hombro_d": {
          "x": 0.349332332611084,
          "y": 0.536379873752594,
          "z": -0.20926517
        },
        "codo_d": {
          "x": 0.10835593193769455,
          "y": 0.6100107431411743,
          "z": -0.51952326
        },
        "muneca_d": {
          "x": -0.035396549850702286,
          "y": 0.5923318266868591,
          "z": -1.1888871
        },
        "hombro_i": {
          "x": 0.6330196261405945,
          "y": 0.5515571236610413,
          "z": -0.20926517
        },
        "codo_i": {
          "x": 0.8923883438110352,
          "y": 0.6720643639564514,
          "z": -0.51952326
        },
        "muneca_i": {
          "x": 1.0385429859161377,
          "y": 0.6151469945907593,
          "z": -1.1888871
        }
      }
    },
    {
      "frame_index": 37,
      "puntos_clave": {
        "nariz": {
          "x": 0.5017321109771729,
          "y": 0.7138674259185791,
          "z": -0.7902351
        },
        "hombro_d": {
          "x": 0.34261342883110046,
          "y": 0.5219569206237793,
          "z": -0.20926517
        },
        "codo_d": {
          "x": 0.11508479714393616,
          "y": 0.6370142698287964,
          "z": -0.51952326
        },
        "muneca_d": {
          "x": -0.05639934539794922,
          "y": 0.6001021862030029,
          "z": -1.1888871
        },
        "hombro_i": {
          "x": 0.620271623134613,
          "y": 0.5430381298065186,
          "z": -0.20926517
        },
        "codo_i": {
          "x": 0.8859353065490723,
          "y": 0.6674049496650696,
          "z": -0.51952326
        },
        "muneca_i": {
          "x": 1.0539921522140503,
          "y": 0.6109641790390015,
          "z": -1.1888871
        }
      }
    },
    {
      "frame_index": 38,
      "puntos_clave": {
        "nariz": {
          "x": 0.4977819621562958,
          "y": 0.7521349191665649,
          "z": -0.7902351
        },
        "hombro_d": {
          "x": 0.3394980728626251,
          "y": 0.5148435235023499,
          "z": -0.20926517
        },
        "codo_d": {
          "x": 0.11047441512346268,
          "y": 0.6346468925476074,
          "z": -0.51952326
        },
        "muneca_d": {
          "x": -0.06941116601228714,
          "y": 0.6167182922363281,
          "z": -1.1888871
        },
        "hombro_i": {
          "x": 0.6524003148078918,
          "y": 0.5428011417388916,
          "z": -0.20926517
        },
        "codo_i": {
          "x": 0.8635964393615723,
          "y": 0.6662956476211548,
          "z": -0.51952326
        },
        "muneca_i": {
          "x": 1.0559074878692627,
          "y": 0.6295443773269653,
          "z": -1.1888871
        }
      }
    },
    {
      "frame_index": 39,
      "puntos_clave": {
        "nariz": {
          "x": 0.4878043532371521,
          "y": 0.7264538407325745,
          "z": -0.7902351
        },
        "hombro_d": {
          "x": 0.36743372678756714,
          "y": 0.520169198513031,
          "z": -0.20926517
        },
        "codo_d": {
          "x": 0.11809661239385605,
          "y": 0.6261017322540283,
          "z": -0.51952326
        },
        "muneca_d": {
          "x": -0.03786948695778847,
          "y": 0.6464945077896118,
          "z": -1.1888871
        },
        "hombro_i": {
          "x": 0.6573180556297302,
          "y": 0.5443126559257507,
          "z": -0.20926517
        },
        "codo_i": {
          "x": 0.8843006491661072,
          "y": 0.6706938147544861,
          "z": -0.51952326
        },
        "muneca_i": {
          "x": 1.0246044397354126,
          "y": 0.6504003405570984,
          "z": -1.1888871
        }
      }
    },
    {
      "frame_index": 40,
      "puntos_clave": {
        "nariz": {
          "x": 0.4947870373725891,
          "y": 0.7355888485908508,
          "z": -0.7902351
        },
        "hombro_d": {
          "x": 0.36391985416412354,
          "y": 0.5440279841423035,
          "z": -0.20926517
        },
        "codo_d": {
          "x": 0.13538749516010284,
          "y": 0.659309446811676,
          "z": -0.51952326
        },
        "muneca_d": {
          "x": -0.04348043352365494,
          "y": 0.6495832800865173,
          "z": -1.1888871
        },
        "hombro_i": {
          "x": 0.6335991024971008,
          "y": 0.5363703370094299,
          "z": -0.20926517
        },
        "codo_i": {
          "x": 0.841070294380188,
          "y": 0.6827753782272339,
          "z": -0.51952326
        },
        "muneca_i": {
          "x": 1.0334643125534058,
          "y": 0.6433725953102112,
          "z": -1.1888871
        }
      }
    },
    {
      "frame_index": 41,
      "puntos_clave": {
        "nariz": {
          "x": 0.5010997653007507,
          "y": 0.7321778535842896,
          "z": -0.7902351
        },
        "hombro_d": {
          "x": 0.3468855321407318,
          "y": 0.5122742056846619,
          "z": -0.20926517
        },
        "codo_d": {
          "x": 0.15198369324207306,
          "y": 0.6566625237464905,
          "z": -0.51952326
        },
        "muneca_d": {
          "x": -0.05449177324771881,
          "y": 0.6786212921142578,
          "z": -1.1888871
        },
        "hombro_i": {
          "x": 0.6499307751655579,
          "y": 0.5519506931304932,
          "z": -0.20926517
        },
        "codo_i": {
          "x": 0.8592975735664368,
          "y": 0.6910513639450073,
          "z": -0.51952326
        },
        "muneca_i": {
          "x": 1.0693327188491821,
          "y": 0.6932563185691833,
          "z": -1.1888871
        }
      }
    },
    {
      "frame_index": 42,
      "puntos_clave": {
        "nariz": {
          "x": 0.5131667852401733,
          "y": 0.7667306065559387,
          "z": -0.7902351
        },
        "hombro_d": {
          "x": 0.3483695387840271,
          "y": 0.5153207182884216,
          "z": -0.20926517
        },
        "codo_d": {
          "x": 0.16066455841064453,
          "y": 0.6587702631950378,
          "z": -0.51952326
        },
        "muneca_d": {
          "x": -0.04800605773925781,
          "y": 0.677383542060852,
          "z": -1.1888871
        },
        "hombro_i": {
          "x": 0.6313713192939758,
          "y": 0.5423479080200195,
          "z": -0.20926517
        },
        "codo_i": {
          "x": 0.8658131957054138,
          "y": 0.7146734595298767,
          "z": -0.51952326
        },
        "muneca_i": {
          "x": 1.0189579725265503,
          "y": 0.6784127950668335,
          "z": -1.1888871
        }
      }
    },
    {
      "frame_index": 43,
      "puntos_clave": {
        "nariz": {
          "x": 0.5031772255897522,
          "y": 0.7533733248710632,
          "z": -0.7902351
        },
        "hombro_d": {
          "x": 0.3581075072288513,
          "y": 0.5643166303634644,
          "z": -0.20926517
        },
        "codo_d": {
          "x": 0.1599949449300766,
          "y": 0.6560467481613159,
          "z": -0.51952326
        },
        "muneca_d": {
          "x": -0.040390968322753906,
          "y": 0.6934961676597595,
          "z": -1.1888871
        },
        "hombro_i": {
          "x": 0.621505856513977,
          "y": 0.5301487445831299,
          "z": -0.20926517
        },
        "codo_i": {
          "x": 0.8397639393806458,
          "y": 0.6977967023849487,
          "z": -0.51952326
        },
        "muneca_i": {
          "x": 1.0362401008605957,
          "y": 0.7085751891136169,
          "z": -1.1888871
        }
      }
    },
    {
      "frame_index": 44,
      "puntos_clave": {
        "nariz": {
          "x": 0.5035855770111084,
          "y": 0.7200830578804016,
          "z": -0.7902351
        },
        "hombro_d": {
          "x": 0.35411757230758667,
          "y": 0.513227105140686,
          "z": -0.20926517
        },
        "codo_d": {
          "x": 0.13570275902748108,
          "y": 0.6787481904029846,
          "z": -0.51952326
        },
        "muneca_d": {
          "x": -0.0386887863278389,
          "y": 0.7190408706665039,
          "z": -1.1888871
        },
        "hombro_i": {
          "x": 0.6653507351875305,
          "y": 0.5614699721336365,
          "z": -0.20926517
        },
        "codo_i": {
          "x": 0.838013231754303,
          "y": 0.7006153464317322,
          "z": -0.51952326
        },
        "muneca_i": {
          "x": 1.0197901725769043,
          "y": 0.724865734577179,
          "z": -1.1888871
        }
      }
    },
    {
      "frame_index": 45,
      "puntos_clave": {
        "nariz": {
          "x": 0.4828588366508484,
          "y": 0.7425549030303955,
          "z": -0.7902351
        },
        "hombro_d": {
          "x": 0.35953277349472046,
          "y": 0.5141870379447937,
          "z": -0.20926517
        },
        "codo_d": {
          "x": 0.1820031702518463,
          "y": 0.686261773109436,
          "z": -0.51952326
        },
        "muneca_d": {
          "x": -0.010409590788185596,
          "y": 0.7104755640029907,
          "z": -1.1888871
        },
        "hombro_i": {
          "x": 0.6534829139709473,
          "y": 0.5357979536056519,
          "z": -0.20926517
        },
        "codo_i": {
          "x": 0.8605591654777527,
          "y": 0.716163694858551,
          "z": -0.51952326
        },
        "muneca_i": {
          "x": 0.9933978319168091,
          "y": 0.747802734375,
          "z": -1.1888871
        }
      }
    },
    {
      "frame_index": 46,
      "puntos_clave": {
        "nariz": {
          "x": 0.5184739828109741,
          "y": 0.7194377779960632,
          "z": -0.7902351
        },
        "hombro_d": {
          "x": 0.37218141555786133,
          "y": 0.5148764848709106,
          "z": -0.20926517
        },
        "codo_d": {
          "x": 0.15940868854522705,
          "y": 0.6632487177848816,
          "z": -0.51952326
        },
        "muneca_d": {
          "x": -0.04173094779253006,
          "y": 0.7118971347808838,
          "z": -1.1888871
        },
        "hombro_i": {
          "x": 0.6305744647979736,
          "y": 0.5213941931724548,
          "z": -0.20926517
        },
        "codo_i": {
          "x": 0.8169407248497009,
          "y": 0.7049111127853394,
          "z": -0.51952326
        },
        "muneca_i": {
          "x": 1.0191175937652588,
          "y": 0.7620770335197449,
          "z": -1.1888871
        }
      }
    },
    {
      "frame_index": 47,
      "puntos_clave": {
        "nariz": {
          "x": 0.5152716040611267,
          "y": 0.7413127422332764,
          "z": -0.7902351
        },
        "hombro_d": {
          "x": 0.3656718134880066,
          "y": 0.5247488617897034,
          "z": -0.20926517
        },
        "codo_d": {
          "x": 0.1623118668794632,
          "y": 0.7079882025718689,
          "z": -0.51952326
        },
        "muneca_d": {
          "x": -0.014049822464585304,
          "y": 0.7434784173965454,
          "z": -1.1888871
        },
        "hombro_i": {
          "x": 0.6332655549049377,
          "y": 0.5367266535758972,
          "z": -0.20926517
        },
        "codo_i": {
          "x": 0.8392205238342285,
          "y": 0.7092585563659668,
          "z": -0.51952326
        },
        "muneca_i": {
          "x": 1.0233851671218872,
          "y": 0.7481476664543152,
          "z": -1.1888871
        }
      }
    },
    {
      "frame_index": 48,
      "puntos_clave": {
        "nariz": {
          "x": 0.4947707951068878,
          "y": 0.731665313243866,
          "z": -0.7902351
        },
        "hombro_d": {
          "x": 0.34461677074432373,
          "y": 0.5032311677932739,
          "z": -0.20926517
        },
        "codo_d": {
          "x": 0.1588285118341446,
          "y": 0.6861410140991211,
          "z": -0.51952326
        },
        "muneca_d": {
          "x": -0.00975493248552084,
          "y": 0.7301926612854004,
          "z": -1.1888871
        },
        "hombro_i": {
          "x": 0.6232619881629944,
          "y": 0.5401078462600708,
          "z": -0.20926517
        },
        "codo_i": {
          "x": 0.8177817463874817,
          "y": 0.7316557765007019,
          "z": -0.51952326
        },
        "muneca_i": {
          "x": 1.0102342367172241,
          "y": 0.7520616054534912,
          "z": -1.1888871
        }
      }
    },
    {
      "frame_index": 49,
      "puntos_clave": {
        "nariz": {
          "x": 0.5152140855789185,
          "y": 0.7499213218688965,
          "z": -0.7902351
        },
        "hombro_d": {
          "x": 0.3500404357910156,
          "y": 0.5270856618881226,
          "z": -0.20926517
        },
        "codo_d": {
          "x": 0.18302273750305176,
          "y": 0.70379638671875,
          "z": -0.51952326
        },
        "muneca_d": {
          "x": 0.0067747654393315315,
          "y": 0.7367847561836243,
          "z": -1.1888871
        },
        "hombro_i": {
          "x": 0.6253630518913269,
          "y": 0.5713708996772766,
          "z": -0.20926517
        },
        "codo_i": {
          "x": 0.808566689491272,
          "y": 0.7073678970336914,
          "z": -0.51952326
        },
        "muneca_i": {
          "x": 0.999439001083374,
          "y": 0.7689695954322815,
          "z": -1.1888871
        }
      }
    },
    {
      "frame_index": 50,
      "puntos_clave": {
        "nariz": {
          "x": 0.4982989728450775,
          "y": 0.7347436547279358,
          "z": -0.7902351
        },
        "hombro_d": {
          "x": 0.348866730928421,
          "y": 0.5045993328094482,
          "z": -0.20926517
        },
        "codo_d": {
          "x": 0.2046758532524109,
          "y": 0.7001373767852783,
          "z": -0.51952326
        },
        "muneca_d": {
          "x": -0.0035539697855710983,
          "y": 0.7643848657608032,
          "z": -1.1888871
        },
        "hombro_i": {
          "x": 0.6476984620094299,
          "y": 0.5342701077461243,
          "z": -0.20926517
        },
        "codo_i": {
          "x": 0.8388209939002991,
          "y": 0.7217419743537903,
          "z": -0.51952326
        },
        "muneca_i": {
          "x": 0.9945243000984192,
          "y": 0.7804116010665894,
          "z": -1.1888871
        }
      }
    },
    {
      "frame_index": 51,
      "puntos_clave": {
        "nariz": {
          "x": 0.5260893106460571,
          "y": 0.7443321347236633,
          "z": -0.7902351
        },
        "hombro_d": {
          "x": 0.3572380542755127,
          "y": 0.5253525376319885,
          "z": -0.20926517
        },
        "codo_d": {
          "x": 0.18071937561035156,
          "y": 0.6978290677070618,
          "z": -0.51952326
        },
        "muneca_d": {
          "x": -0.019304949790239334,
          "y": 0.7469750642776489,
          "z": -1.1888871
        },
        "hombro_i": {
          "x": 0.650894284248352,
          "y": 0.5378336310386658,
          "z": -0.20926517
        },
        "codo_i": {
          "x": 0.8340590596199036,
          "y": 0.7356033325195312,
          "z": -0.51952326
        },
        "muneca_i": {
          "x": 0.9977574944496155,
          "y": 0.7913309335708618,
          "z": -1.1888871
        }
      }
    },
    {
      "frame_index": 52,
      "puntos_clave": {
        "nariz": {
          "x": 0.5232757925987244,
          "y": 0.7467489242553711,
          "z": -0.7902351
        },
        "hombro_d": {
          "x": 0.3720847964286804,
          "y": 0.5151110291481018,
          "z": -0.20926517
        },
        "codo_d": {
          "x": 0.1940292865037918,
          "y": 0.710900604724884,
          "z": -0.51952326
        },
        "muneca_d": {
          "x": 0.0010846410878002644,
          "y": 0.7552934885025024,
          "z": -1.1888871
        },
        "hombro_i": {
          "x": 0.6246961355209351,
          "y": 0.5102947354316711,
          "z": -0.20926517
        },
        "codo_i": {
          "x": 0.8005040287971497,
          "y": 0.7273436188697815,
          "z": -0.51952326
        },
        "muneca_i": {
          "x": 0.9884271025657654,
          "y": 0.780631422996521,
          "z": -1.1888871
        }
      }
    },
    {
      "frame_index": 53,
      "puntos_clave": {
        "nariz": {
          "x": 0.5024089217185974,
          "y": 0.7407150864601135,
          "z": -0.7902351
        },
        "hombro_d": {
          "x": 0.3698832392692566,
          "y": 0.5084490776062012,
          "z": -0.20926517
        },
        "codo_d": {
          "x": 0.1829407960176468,
          "y": 0.6984310150146484,
          "z": -0.51952326
        },
        "muneca_d": {
          "x": 0.010966518893837929,
          "y": 0.7393108606338501,
          "z": -1.1888871
        },
        "hombro_i": {
          "x": 0.6269963979721069,
          "y": 0.5427135825157166,
          "z": -0.20926517
        },
        "codo_i": {
          "x": 0.8211323022842407,
          "y": 0.7285036444664001,
          "z": -0.51952326
        },
        "muneca_i": {
          "x": 0.9783475995063782,
          "y": 0.7930614948272705,
          "z": -1.1888871
        }
      }
    },
    {
      "frame_index": 54,
      "puntos_clave": {
        "nariz": {
          "x": 0.5060185194015503,
          "y": 0.7293586730957031,
          "z": -0.7902351
        },
        "hombro_d": {
          "x": 0.36633235216140747,
          "y": 0.4981513023376465,
          "z": -0.20926517
        },
        "codo_d": {
          "x": 0.17101448774337769,
          "y": 0.7276955842971802,
          "z": -0.51952326
        },
        "muneca_d": {
          "x": 0.012563505209982395,
          "y": 0.7417836785316467,
          "z": -1.1888871
        },
        "hombro_i": {
          "x": 0.6343898773193359,
          "y": 0.5574890375137329,
          "z": -0.20926517
        },
        "codo_i": {
          "x": 0.8119532465934753,
          "y": 0.7130417823791504,
          "z": -0.51952326
        },
        "muneca_i": {
          "x": 0.9985808730125427,
          "y": 0.7928619384765625,
          "z": -1.1888871
        }
      }
    },
    {
      "frame_index": 55,
      "puntos_clave": {
        "nariz": {
          "x": 0.5195376873016357,
          "y": 0.7178557515144348,
          "z": -0.7902351
        },
        "hombro_d": {
          "x": 0.36072707176208496,
          "y": 0.5269564986228943,
          "z": -0.20926517
        },
        "codo_d": {
          "x": 0.1939169317483902,
          "y": 0.7041357159614563,
          "z": -0.51952326
        },
        "muneca_d": {
          "x": 0.02030239999294281,
          "y": 0.7723935842514038,
          "z": -1.1888871
        },
        "hombro_i": {
          "x": 0.6310665011405945,
          "y": 0.5359926819801331,
          "z": -0.20926517
        },
        "codo_i": {
          "x": 0.832805871963501,
          "y": 0.746514081954956,
          "z": -0.51952326
        },
        "muneca_i": {
          "x": 0.9737299084663391,
          "y": 0.773367166519165,
          "z": -1.1888871
        }
      }
    }
  ]
}